czo/__init__.py
czo/data/__init__.py
czo/data/_addr.py
czo/data/_country.py
czo/data/_data.py
czo/data/_housing.py
czo/data/_internal_utils.py
czo/data/_shop_sign.py
czo/py.typed
czo/utils/__init__.py
czo/utils/datetime.py
czo/utils/faker.py
czo/utils/net.py
czo/utils/paths.py
czo/utils/randgen.py
czo-0.3.2.dist-info/WHEEL
czo-0.3.2.dist-info/METADATA
czo-0.3.2.dist-info/RECORD
